stats_compass_mcp/__init__.py
stats_compass_mcp/cli.py
stats_compass_mcp/local/__init__.py
stats_compass_mcp/local/__main__.py
stats_compass_mcp/local/install.py
stats_compass_mcp/local/server.py
stats_compass_mcp/local/tools.py
stats_compass_mcp/remote/__init__.py
stats_compass_mcp/remote/__main__.py
stats_compass_mcp/remote/bridge.py
stats_compass_mcp/remote/image_utils.py
stats_compass_mcp/remote/install.py
stats_compass_mcp/remote/parent_tools.py
stats_compass_mcp/remote/server.py
stats_compass_mcp/remote/session.py
stats_compass_mcp/remote/storage.py
stats_compass_mcp/remote/workflow_tools.py
stats_compass_mcp/workflow_summary.py
stats_compass_mcp-0.1.12.dist-info/LICENSE
stats_compass_mcp-0.1.12.dist-info/METADATA
stats_compass_mcp-0.1.12.dist-info/WHEEL
stats_compass_mcp-0.1.12.dist-info/entry_points.txt
stats_compass_mcp-0.1.12.dist-info/RECORD
