Metadata-Version: 2.3
Name: stats-compass-mcp
Version: 0.1.12
Summary: MCP server exposing stats-compass-core tools to LLMs like ChatGPT, Claude, and Gemini
License: MIT
Keywords: mcp,llm,data-science,pandas,ai-agents,chatgpt,claude
Author: Olatunji Ogunbiyi
Author-email: oogunbiyi21@users.noreply.github.com
Requires-Python: >=3.11,<4.0
Classifier: Development Status :: 3 - Alpha
Classifier: Intended Audience :: Developers
Classifier: Intended Audience :: Science/Research
Classifier: License :: OSI Approved :: MIT License
Classifier: Programming Language :: Python :: 3
Classifier: Programming Language :: Python :: 3.11
Classifier: Programming Language :: Python :: 3.12
Classifier: Programming Language :: Python :: 3.13
Classifier: Topic :: Scientific/Engineering
Classifier: Topic :: Software Development :: Libraries :: Python Modules
Requires-Dist: boto3 (>=1.42.25,<2.0.0)
Requires-Dist: fastmcp (>=2.14.2,<3.0.0)
Requires-Dist: mcp (>=1.0.0,<2.0.0)
Requires-Dist: stats-compass-core[all] (>=0.1.16,<0.2.0)
